{
  "users": {},
  "products": {},
  "category": {},
  "banner": [
    {
      "id": 1,
      "image": "https://bizweb.sapocdn.net/100/438/408/themes/878697/assets/slider_5.jpg?1664614031289",
      "active": true
    },
    {
      "id": 2,
      "image": "https://bizweb.sapocdn.net/100/438/408/themes/878697/assets/slider_1.jpg?1664614031289",
      "active": true
    },
    {
      "id": 3,
      "image": "https://bizweb.sapocdn.net/100/438/408/themes/878697/assets/slider_2.jpg?1664614031289",
      "active": true
    }
  ]
}
